CHANGES.txt
MANIFEST.in
README.rst
setup.cfg
setup.py
quantities/__init__.py
quantities/decorators.py
quantities/dimensionality.py
quantities/markup.py
quantities/quantity.py
quantities/registry.py
quantities/umath.py
quantities/uncertainquantity.py
quantities/unitquantity.py
quantities/constants/NIST_codata.txt
quantities/constants/__init__.py
quantities/constants/_codata.py
quantities/constants/_utils.py
quantities/constants/alpha.py
quantities/constants/astronomy.py
quantities/constants/atomicunits.py
quantities/constants/deuteron.py
quantities/constants/electromagnetism.py
quantities/constants/electron.py
quantities/constants/helion.py
quantities/constants/mathematical.py
quantities/constants/muon.py
quantities/constants/naturalunits.py
quantities/constants/neutron.py
quantities/constants/proton.py
quantities/constants/quantum.py
quantities/constants/relationships.py
quantities/constants/statisticalmechanics.py
quantities/constants/tau.py
quantities/constants/triton.py
quantities/constants/weak.py
quantities/constants/xray.py
quantities/tests/__init__.py
quantities/tests/common.py
quantities/tests/test_arithmetic.py
quantities/tests/test_comparison.py
quantities/tests/test_constants.py
quantities/tests/test_conversion.py
quantities/tests/test_dimensionality.py
quantities/tests/test_formatting.py
quantities/tests/test_methods.py
quantities/tests/test_persistence.py
quantities/tests/test_umath.py
quantities/tests/test_uncertainty.py
quantities/tests/test_units.py
quantities/units/__init__.py
quantities/units/acceleration.py
quantities/units/angle.py
quantities/units/area.py
quantities/units/compound.py
quantities/units/concentration.py
quantities/units/dimensionless.py
quantities/units/electromagnetism.py
quantities/units/energy.py
quantities/units/force.py
quantities/units/frequency.py
quantities/units/heat.py
quantities/units/information.py
quantities/units/length.py
quantities/units/mass.py
quantities/units/power.py
quantities/units/prefixes.py
quantities_scidash.egg-info/PKG-INFO
quantities_scidash.egg-info/SOURCES.txt
quantities_scidash.egg-info/dependency_links.txt
quantities_scidash.egg-info/top_level.txt