Metadata-Version: 2.1
Name: quantities-scidash
Version: 0.12.4.3
Summary: Support for physical quantities with units, based on numpy
Home-page: http://python-quantities.readthedocs.io/
Author: Darren Dale
Author-email: dsdale24@gmail.com
License: BSD
Download-URL: http://pypi.python.org/pypi/quantities
Keywords: quantities,units,physical,constants
Platform: Any
Requires: python (>=3.6)
Requires: numpy (>=1.13)
